[{"authors":["admin"],"categories":null,"content":"I am an Freshman Undergradute Student at Indian Institute Of Science pursuing BS (Research) with intended major in Physics. I love pondering over tough problems that stimulate my neurons, especially in Physics and Mathemtics. I am interested in Quantum Computing, Information Theory and Cosmology but am open to any topic that tickles my fancy.\n","date":-62135596800,"expirydate":-62135596800,"kind":"term","lang":"en","lastmod":-62135596800,"objectID":"2525497d367e79493fd32b198b28f040","permalink":"https://anish-ku.github.io/author/anish-kumar/","publishdate":"0001-01-01T00:00:00Z","relpermalink":"/author/anish-kumar/","section":"authors","summary":"I am an Freshman Undergradute Student at Indian Institute Of Science pursuing BS (Research) with intended major in Physics. I love pondering over tough problems that stimulate my neurons, especially in Physics and Mathemtics.","tags":null,"title":"Anish Kumar","type":"authors"}]